clustcrdist/__init__.py
clustcrdist/_version.py
clustcrdist/analysis.py
clustcrdist/background.py
clustcrdist/datasets.py
clustcrdist/distance.py
clustcrdist/encoding.py
clustcrdist/export.py
clustcrdist/indexing.py
clustcrdist/neighbors.py
clustcrdist/pgen.py
clustcrdist/readers.py
clustcrdist/repertoire.py
clustcrdist/run_pipeline.py
clustcrdist/tools.py
clustcrdist/viz.py
clustcrdist/constants/__init__.py
clustcrdist/constants/base.py
clustcrdist/constants/datasets.py
clustcrdist/constants/distance.py
clustcrdist/constants/distributions.py
clustcrdist/constants/hashing.py
clustcrdist/constants/parsing.py
clustcrdist/constants/preprocessing.py
clustcrdist/constants/tools.py
clustcrdist/constants/data/adaptive_imgt_mapping.csv
clustcrdist/constants/data/adaptive_v_fam_to_imgt_gene.txt
clustcrdist/constants/data/alphabeta_db.tsv
clustcrdist/constants/data/combo_xcr.tsv
clustcrdist/constants/data/imgt_reference.tsv
clustcrdist/constants/data/vgene_to_cdr.txt
clustcrdist/constants/data/vdjdb/LICENSE.txt
clustcrdist/constants/data/vdjdb/cluster_members.txt
clustcrdist/constants/data/vdjdb/latest-version.txt
clustcrdist/constants/data/vdjdb/motif_pwms.txt
clustcrdist/constants/data/vdjdb/vdjdb.meta.txt
clustcrdist/constants/data/vdjdb/vdjdb.slim.meta.txt
clustcrdist/constants/data/vdjdb/vdjdb.slim.txt
clustcrdist/constants/data/vdjdb/vdjdb.txt
clustcrdist/constants/data/vdjdb/vdjdb_full.txt
clustcrdist/constants/data/vdjdb/vdjdb_human.txt
clustcrdist/constants/data/vdjdb/vdjdb_mouse.txt
clustcrdist/constants/modules/clustermap/exception.py
clustcrdist/constants/modules/clustermap/heatmap.py
clustcrdist/constants/modules/olga/__init__.py
clustcrdist/constants/modules/olga/compute_pgen.py
clustcrdist/constants/modules/olga/generate_sequences.py
clustcrdist/constants/modules/olga/generation_probability.py
clustcrdist/constants/modules/olga/load_model.py
clustcrdist/constants/modules/olga/olga_directed.py
clustcrdist-0.1.5.dist-info/LICENSE
clustcrdist-0.1.5.dist-info/METADATA
clustcrdist-0.1.5.dist-info/WHEEL
clustcrdist-0.1.5.dist-info/entry_points.txt
clustcrdist-0.1.5.dist-info/top_level.txt
clustcrdist-0.1.5.dist-info/RECORD
