Metadata-Version: 2.1
Name: clustcrdist
Version: 0.1.5
Summary: Pairwise distance calculation and neighborhood enrichment analysis of TCR repertoires
Home-page: https://github.com/svalkiers/immune_response_detection
Author: Sebastiaan Valkiers
Author-email: sebastiaan.valkiers@uantwerpen.be
Maintainer: Sebastiaan Valkiers
Maintainer-email: sebastiaan.valkiers@uantwerpen.be
License: MIT
Classifier: Programming Language :: Python :: 3
Classifier: Programming Language :: Python :: 3.9
Classifier: License :: OSI Approved :: MIT License
Classifier: Operating System :: OS Independent
Requires-Python: >=3.9
License-File: LICENSE
Requires-Dist: numpy >=1.23.5
Requires-Dist: pandas >=1.5.2
Requires-Dist: faiss-cpu ==1.7.3
Requires-Dist: scipy ==1.9.3
Requires-Dist: scikit-learn ==1.2.0
Requires-Dist: pynndescent ==0.5.8
Requires-Dist: igraph ==0.10.3
Requires-Dist: networkx ==3.0
Requires-Dist: olga ==1.2.4
Requires-Dist: leidenalg ==0.9.1
Requires-Dist: logomaker ==0.8
Requires-Dist: statsmodels ==0.14.0
Requires-Dist: matplotlib >=3.6.2
Requires-Dist: seaborn >=0.13.2
Requires-Dist: biopython >=1.84
Requires-Dist: parmap ==1.6.0
Requires-Dist: pip
